profanity_filter/__init__.py
profanity_filter/analysis/__init__.py
profanity_filter/analysis/deep.py
profanity_filter/analysis/morphological.py
profanity_filter/analysis/multilingual.py
profanity_filter/config.py
profanity_filter/console.py
profanity_filter/data/en_profane_words.txt
profanity_filter/data/ru_profane_words.txt
profanity_filter/profanity_filter.py
profanity_filter/spacy_component.py
profanity_filter/spacy_utlis.py
profanity_filter/types_.py
profanity_filter/web.py
profanity_filter-1.3.2.dist-info/entry_points.txt
profanity_filter-1.3.2.dist-info/LICENSE
profanity_filter-1.3.2.dist-info/WHEEL
profanity_filter-1.3.2.dist-info/METADATA
profanity_filter-1.3.2.dist-info/RECORD
