Metadata-Version: 2.1
Name: profanity-filter
Version: 1.3.2
Summary: A Python library for detecting and filtering profanity
Home-page: https://github.com/rominf/profanity-filter
License: GPL-3.0+
Keywords: library,profanity,filter,censor
Author: Roman Inflianskas
Author-email: infroma@gmail.com
Maintainer: Roman Inflianskas
Maintainer-email: infroma@gmail.com
Requires-Python: >=3.6,<4.0
Classifier: Development Status :: 5 - Production/Stable
Classifier: Environment :: Console
Classifier: Intended Audience :: Developers
Classifier: License :: OSI Approved :: GNU General Public License v3 or later (GPLv3+)
Classifier: Natural Language :: English
Classifier: Natural Language :: Russian
Classifier: Programming Language :: Python :: 3
Classifier: Programming Language :: Python :: 3.6
Classifier: Programming Language :: Python :: 3.7
Classifier: Programming Language :: Python :: 3.8
Classifier: Topic :: Software Development :: Libraries :: Python Modules
Classifier: Topic :: Text Processing :: Filters
Classifier: Topic :: Text Processing :: Linguistic
Provides-Extra: deep-analysis
Provides-Extra: multilingual
Provides-Extra: pymorphy2-ru
Provides-Extra: pymorphy2-uk
Provides-Extra: web
Requires-Dist: PyICU (>=2.4,<3.0); extra == "multilingual"
Requires-Dist: appdirs (>=1.4.3,<2.0.0); extra == "web"
Requires-Dist: cached-property (>=1.5,<2.0)
Requires-Dist: dataclasses (>=0.6.0,<0.7.0); python_version >= "3.6" and python_version < "3.7"
Requires-Dist: fastapi (>=0.45.0,<0.46.0); extra == "web"
Requires-Dist: hunspell (>=0.5.5,<0.6.0); extra == "deep-analysis"
Requires-Dist: more-itertools (>=8.0,<9.0)
Requires-Dist: ordered-set (>=3.0,<4.0)
Requires-Dist: ordered-set-stubs (>=0.1.3,<0.2.0)
Requires-Dist: poetry-version (>=0.1.3,<0.2.0)
Requires-Dist: polyglot (>=16.7,<17.0); extra == "multilingual"
Requires-Dist: pycld2 (==0.31); extra == "multilingual"
Requires-Dist: pydantic (>=1.3,<2.0)
Requires-Dist: pymorphy2-dicts-ru (>=2.4.404381,<3.0.0); extra == "pymorphy2-ru"
Requires-Dist: pymorphy2-dicts-uk (>=2.4.1,<3.0.0); extra == "pymorphy2-uk"
Requires-Dist: python-Levenshtein (>=0.12.0,<0.13.0); extra == "deep-analysis"
Requires-Dist: redis (>=3.2,<4.0)
Requires-Dist: regex (>=2019.12.20,<2020.0.0); extra == "deep-analysis"
Requires-Dist: ruamel.yaml (>=0.15.89,<0.16.0)
Requires-Dist: spacy (>=2.0,<3.0)
Requires-Dist: uvicorn (>=0.11.1,<0.12.0); extra == "web"
Project-URL: Repository, https://github.com/rominf/profanity-filter
